README.md
requirements.txt
setup.py
fx_nb_log.egg-info/PKG-INFO
fx_nb_log.egg-info/SOURCES.txt
fx_nb_log.egg-info/dependency_links.txt
fx_nb_log.egg-info/requires.txt
fx_nb_log.egg-info/top_level.txt
nb_log/__init__.py
nb_log/handlers.py
nb_log/log_manager.py
nb_log/monkey_print.py
nb_log/nb_log_config_default.py
nb_log/set_nb_log_config.py