Metadata-Version: 2.1
Name: fx-nb-log
Version: 3.4.9
Summary: modified nb_log
Home-page: https://gitee.com/toosimple-tools/nb_log
Author: ydf
Author-email: ydf0509@sohu.com
Maintainer: fx
Maintainer-email: fengxin@826.com
License: BSD License
Keywords: logging,logger,multiprocess file handler,color handler
Platform: all
Classifier: Development Status :: 4 - Beta
Classifier: Operating System :: OS Independent
Classifier: Intended Audience :: Developers
Classifier: License :: OSI Approved :: BSD License
Classifier: Programming Language :: Python :: 3.7
Classifier: Topic :: Software Development :: Libraries
